learn2map/ALOS_calculator.py
learn2map/NBAR.py
learn2map/__init__.py
learn2map/ba_raster_cut.py
learn2map/data_learning.py
learn2map/hensen_01_18.py
learn2map/hensen_500m.py
learn2map/landsat_merge.py
learn2map/mcd15a3v6_merge.py
learn2map/mcd43a4_merge_monthly.py
learn2map/mod_lc_resample.py
learn2map/raster_tools.py
learn2map/rf_estimator.py
learn2map/test01.py
learn2map/test_merge_alos.py
learn2map-0.7.1.dist-info/LICENSE
learn2map-0.7.1.dist-info/METADATA
learn2map-0.7.1.dist-info/PKG-INFO.sync-conflict-20180813-181239-TRTRPBN
learn2map-0.7.1.dist-info/PKG-INFO.sync-conflict-20181204-085011-B4TZJBA
learn2map-0.7.1.dist-info/WHEEL
learn2map-0.7.1.dist-info/entry_points.txt
learn2map-0.7.1.dist-info/top_level.txt
learn2map-0.7.1.dist-info/RECORD
