Metadata-Version: 2.1
Name: learn2map
Version: 0.7.1
Summary: Spatial mapping from remote sensing data
Home-page: https://gitlab.com/alanxuliang/a1610_learn2map
Author: Alan Xu
Author-email: bireme@gmail.com
License: MIT
Keywords: Forest Biomass
Platform: UNKNOWN
Classifier: Development Status :: 3 - Alpha
Classifier: Intended Audience :: Science/Research
Classifier: Topic :: Scientific/Engineering :: GIS
Classifier: License :: OSI Approved :: MIT License
Classifier: Programming Language :: Python :: 3.5
License-File: LICENSE
Requires-Dist: numpy
Requires-Dist: pandas
Requires-Dist: lxml
